{
    "Data": {
        "Objectives": [
            {
                "Type": "statemachine",
                "Id": "2519ab48-537c-41ab-adab-98332315a2e5",
                "BriefingText": {
                    "$loc": {
                        "key": "UI_CONTRACT_GENERAL_OBJ_KILL",
                        "data": "$($repository df5c1078-aa9e-4649-b5a4-e49ec984cc89).Name"
                    }
                },
                "HUDTemplate": {
                    "display": {
                        "$loc": {
                            "key": "UI_CONTRACT_GENERAL_OBJ_KILL",
                            "data": "$($repository df5c1078-aa9e-4649-b5a4-e49ec984cc89).Name"
                        }
                    }
                },
                "Category": "primary",
                "Definition": {
                    "Scope": "Hit",
                    "Context": {
                        "Targets": [
                            "df5c1078-aa9e-4649-b5a4-e49ec984cc89"
                        ]
                    },
                    "States": {
                        "Start": {
                            "Kill": [
                                {
                                    "Condition": {
                                        "$eq": [
                                            "$Value.RepositoryId",
                                            "df5c1078-aa9e-4649-b5a4-e49ec984cc89"
                                        ]
                                    },
                                    "Transition": "Success"
                                }
                            ]
                        }
                    }
                },
                "TargetConditions": [
                    {
                        "Type": "hitmansuit",
                        "RepositoryId": "75759271-e236-4b33-8dd5-7e502c958d05",
                        "HardCondition": false,
                        "ObjectiveId": "51fe54fc-2895-4534-b33d-50e111e5efb5",
                        "KillMethod": ""
                    },
                    {
                        "Type": "killmethod",
                        "RepositoryId": "1264f20b-b901-4d36-bc03-a9115709b531",
                        "HardCondition": false,
                        "ObjectiveId": "53251d9c-147e-4677-8571-d18104f52bb3",
                        "KillMethod": "sniperrifle"
                    }
                ]
            },
            {
                "Type": "statemachine",
                "Id": "51fe54fc-2895-4534-b33d-50e111e5efb5",
                "Category": "secondary",
                "Definition": {
                    "Scope": "Hit",
                    "Context": {
                        "Targets": [
                            "df5c1078-aa9e-4649-b5a4-e49ec984cc89"
                        ]
                    },
                    "States": {
                        "Start": {
                            "Kill": [
                                {
                                    "Condition": {
                                        "$and": [
                                            {
                                                "$eq": [
                                                    "$Value.RepositoryId",
                                                    "df5c1078-aa9e-4649-b5a4-e49ec984cc89"
                                                ]
                                            },
                                            {
                                                "$eq": [
                                                    "$Value.OutfitIsHitmanSuit",
                                                    true
                                                ]
                                            }
                                        ]
                                    },
                                    "Transition": "Success"
                                },
                                {
                                    "Condition": {
                                        "$eq": [
                                            "$Value.RepositoryId",
                                            "df5c1078-aa9e-4649-b5a4-e49ec984cc89"
                                        ]
                                    },
                                    "Transition": "Failure"
                                }
                            ]
                        }
                    }
                }
            },
            {
                "Type": "statemachine",
                "Id": "53251d9c-147e-4677-8571-d18104f52bb3",
                "Category": "secondary",
                "Definition": {
                    "Scope": "Hit",
                    "Context": {
                        "Targets": [
                            "df5c1078-aa9e-4649-b5a4-e49ec984cc89"
                        ]
                    },
                    "States": {
                        "Start": {
                            "Kill": [
                                {
                                    "Condition": {
                                        "$and": [
                                            {
                                                "$eq": [
                                                    "$Value.RepositoryId",
                                                    "df5c1078-aa9e-4649-b5a4-e49ec984cc89"
                                                ]
                                            },
                                            {
                                                "$any": {
                                                    "?": {
                                                        "$eq": [
                                                            "$.#",
                                                            "sniperrifle"
                                                        ]
                                                    },
                                                    "in": [
                                                        "$Value.KillMethodBroad",
                                                        "$Value.KillMethodStrict"
                                                    ]
                                                }
                                            }
                                        ]
                                    },
                                    "Transition": "Success"
                                },
                                {
                                    "Condition": {
                                        "$eq": [
                                            "$Value.RepositoryId",
                                            "df5c1078-aa9e-4649-b5a4-e49ec984cc89"
                                        ]
                                    },
                                    "Transition": "Failure"
                                }
                            ]
                        }
                    }
                }
            },
            {
                "Type": "statemachine",
                "Id": "6a05b0f9-c79a-4d5b-9e69-2b52595b61ea",
                "BriefingText": {
                    "$loc": {
                        "key": "UI_CONTRACT_GENERAL_OBJ_KILL",
                        "data": "$($repository aaf3d76b-c7d1-4987-882e-cedb8be96e35).Name"
                    }
                },
                "HUDTemplate": {
                    "display": {
                        "$loc": {
                            "key": "UI_CONTRACT_GENERAL_OBJ_KILL",
                            "data": "$($repository aaf3d76b-c7d1-4987-882e-cedb8be96e35).Name"
                        }
                    }
                },
                "Category": "primary",
                "Definition": {
                    "Scope": "Hit",
                    "Context": {
                        "Targets": [
                            "aaf3d76b-c7d1-4987-882e-cedb8be96e35"
                        ]
                    },
                    "States": {
                        "Start": {
                            "Kill": [
                                {
                                    "Condition": {
                                        "$eq": [
                                            "$Value.RepositoryId",
                                            "aaf3d76b-c7d1-4987-882e-cedb8be96e35"
                                        ]
                                    },
                                    "Transition": "Success"
                                }
                            ]
                        }
                    }
                },
                "TargetConditions": [
                    {
                        "Type": "hitmansuit",
                        "RepositoryId": "75759271-e236-4b33-8dd5-7e502c958d05",
                        "HardCondition": false,
                        "ObjectiveId": "b6c2ded3-71bc-47d9-8744-2a17b3e73796",
                        "KillMethod": ""
                    },
                    {
                        "Type": "killmethod",
                        "RepositoryId": "1264f20b-b901-4d36-bc03-a9115709b531",
                        "HardCondition": false,
                        "ObjectiveId": "3491cc4b-5748-4a15-b4d5-bc791333e01a",
                        "KillMethod": "sniperrifle"
                    }
                ]
            },
            {
                "Type": "statemachine",
                "Id": "b6c2ded3-71bc-47d9-8744-2a17b3e73796",
                "Category": "secondary",
                "Definition": {
                    "Scope": "Hit",
                    "Context": {
                        "Targets": [
                            "aaf3d76b-c7d1-4987-882e-cedb8be96e35"
                        ]
                    },
                    "States": {
                        "Start": {
                            "Kill": [
                                {
                                    "Condition": {
                                        "$and": [
                                            {
                                                "$eq": [
                                                    "$Value.RepositoryId",
                                                    "aaf3d76b-c7d1-4987-882e-cedb8be96e35"
                                                ]
                                            },
                                            {
                                                "$eq": [
                                                    "$Value.OutfitIsHitmanSuit",
                                                    true
                                                ]
                                            }
                                        ]
                                    },
                                    "Transition": "Success"
                                },
                                {
                                    "Condition": {
                                        "$eq": [
                                            "$Value.RepositoryId",
                                            "aaf3d76b-c7d1-4987-882e-cedb8be96e35"
                                        ]
                                    },
                                    "Transition": "Failure"
                                }
                            ]
                        }
                    }
                }
            },
            {
                "Type": "statemachine",
                "Id": "3491cc4b-5748-4a15-b4d5-bc791333e01a",
                "Category": "secondary",
                "Definition": {
                    "Scope": "Hit",
                    "Context": {
                        "Targets": [
                            "aaf3d76b-c7d1-4987-882e-cedb8be96e35"
                        ]
                    },
                    "States": {
                        "Start": {
                            "Kill": [
                                {
                                    "Condition": {
                                        "$and": [
                                            {
                                                "$eq": [
                                                    "$Value.RepositoryId",
                                                    "aaf3d76b-c7d1-4987-882e-cedb8be96e35"
                                                ]
                                            },
                                            {
                                                "$any": {
                                                    "?": {
                                                        "$eq": [
                                                            "$.#",
                                                            "sniperrifle"
                                                        ]
                                                    },
                                                    "in": [
                                                        "$Value.KillMethodBroad",
                                                        "$Value.KillMethodStrict"
                                                    ]
                                                }
                                            }
                                        ]
                                    },
                                    "Transition": "Success"
                                },
                                {
                                    "Condition": {
                                        "$eq": [
                                            "$Value.RepositoryId",
                                            "aaf3d76b-c7d1-4987-882e-cedb8be96e35"
                                        ]
                                    },
                                    "Transition": "Failure"
                                }
                            ]
                        }
                    }
                }
            },
            {
                "Type": "statemachine",
                "Id": "acaf277c-c58b-4b7b-919e-448d12332d97",
                "BriefingText": {
                    "$loc": {
                        "key": "UI_CONTRACT_GENERAL_OBJ_KILL",
                        "data": "$($repository 5b5c9cd5-4f21-422b-828c-b41e8c777c2c).Name"
                    }
                },
                "HUDTemplate": {
                    "display": {
                        "$loc": {
                            "key": "UI_CONTRACT_GENERAL_OBJ_KILL",
                            "data": "$($repository 5b5c9cd5-4f21-422b-828c-b41e8c777c2c).Name"
                        }
                    }
                },
                "Category": "primary",
                "Definition": {
                    "Scope": "Hit",
                    "Context": {
                        "Targets": [
                            "5b5c9cd5-4f21-422b-828c-b41e8c777c2c"
                        ]
                    },
                    "States": {
                        "Start": {
                            "Kill": [
                                {
                                    "Condition": {
                                        "$eq": [
                                            "$Value.RepositoryId",
                                            "5b5c9cd5-4f21-422b-828c-b41e8c777c2c"
                                        ]
                                    },
                                    "Transition": "Success"
                                }
                            ]
                        }
                    }
                },
                "TargetConditions": [
                    {
                        "Type": "hitmansuit",
                        "RepositoryId": "75759271-e236-4b33-8dd5-7e502c958d05",
                        "HardCondition": false,
                        "ObjectiveId": "613d0abd-bdd0-4972-be73-435690a3cd92",
                        "KillMethod": ""
                    },
                    {
                        "Type": "killmethod",
                        "RepositoryId": "1264f20b-b901-4d36-bc03-a9115709b531",
                        "HardCondition": false,
                        "ObjectiveId": "fe8b4d3b-427f-49de-b7a4-0ed77972aa46",
                        "KillMethod": "sniperrifle"
                    }
                ]
            },
            {
                "Type": "statemachine",
                "Id": "613d0abd-bdd0-4972-be73-435690a3cd92",
                "Category": "secondary",
                "Definition": {
                    "Scope": "Hit",
                    "Context": {
                        "Targets": [
                            "5b5c9cd5-4f21-422b-828c-b41e8c777c2c"
                        ]
                    },
                    "States": {
                        "Start": {
                            "Kill": [
                                {
                                    "Condition": {
                                        "$and": [
                                            {
                                                "$eq": [
                                                    "$Value.RepositoryId",
                                                    "5b5c9cd5-4f21-422b-828c-b41e8c777c2c"
                                                ]
                                            },
                                            {
                                                "$eq": [
                                                    "$Value.OutfitIsHitmanSuit",
                                                    true
                                                ]
                                            }
                                        ]
                                    },
                                    "Transition": "Success"
                                },
                                {
                                    "Condition": {
                                        "$eq": [
                                            "$Value.RepositoryId",
                                            "5b5c9cd5-4f21-422b-828c-b41e8c777c2c"
                                        ]
                                    },
                                    "Transition": "Failure"
                                }
                            ]
                        }
                    }
                }
            },
            {
                "Type": "statemachine",
                "Id": "fe8b4d3b-427f-49de-b7a4-0ed77972aa46",
                "Category": "secondary",
                "Definition": {
                    "Scope": "Hit",
                    "Context": {
                        "Targets": [
                            "5b5c9cd5-4f21-422b-828c-b41e8c777c2c"
                        ]
                    },
                    "States": {
                        "Start": {
                            "Kill": [
                                {
                                    "Condition": {
                                        "$and": [
                                            {
                                                "$eq": [
                                                    "$Value.RepositoryId",
                                                    "5b5c9cd5-4f21-422b-828c-b41e8c777c2c"
                                                ]
                                            },
                                            {
                                                "$any": {
                                                    "?": {
                                                        "$eq": [
                                                            "$.#",
                                                            "sniperrifle"
                                                        ]
                                                    },
                                                    "in": [
                                                        "$Value.KillMethodBroad",
                                                        "$Value.KillMethodStrict"
                                                    ]
                                                }
                                            }
                                        ]
                                    },
                                    "Transition": "Success"
                                },
                                {
                                    "Condition": {
                                        "$eq": [
                                            "$Value.RepositoryId",
                                            "5b5c9cd5-4f21-422b-828c-b41e8c777c2c"
                                        ]
                                    },
                                    "Transition": "Failure"
                                }
                            ]
                        }
                    }
                }
            },
            {
                "Type": "statemachine",
                "Id": "690825bf-499d-4ad7-9b50-297e1b2763f4",
                "BriefingText": {
                    "$loc": {
                        "key": "UI_CONTRACT_GENERAL_OBJ_KILL",
                        "data": "$($repository 9a179346-f61f-4239-b46e-0e540ee34082).Name"
                    }
                },
                "HUDTemplate": {
                    "display": {
                        "$loc": {
                            "key": "UI_CONTRACT_GENERAL_OBJ_KILL",
                            "data": "$($repository 9a179346-f61f-4239-b46e-0e540ee34082).Name"
                        }
                    }
                },
                "Category": "primary",
                "Definition": {
                    "Scope": "Hit",
                    "Context": {
                        "Targets": [
                            "9a179346-f61f-4239-b46e-0e540ee34082"
                        ]
                    },
                    "States": {
                        "Start": {
                            "Kill": [
                                {
                                    "Condition": {
                                        "$eq": [
                                            "$Value.RepositoryId",
                                            "9a179346-f61f-4239-b46e-0e540ee34082"
                                        ]
                                    },
                                    "Transition": "Success"
                                }
                            ]
                        }
                    }
                },
                "TargetConditions": [
                    {
                        "Type": "hitmansuit",
                        "RepositoryId": "75759271-e236-4b33-8dd5-7e502c958d05",
                        "HardCondition": false,
                        "ObjectiveId": "d4e04980-d5ae-4d73-9823-cd278034640d",
                        "KillMethod": ""
                    },
                    {
                        "Type": "killmethod",
                        "RepositoryId": "1264f20b-b901-4d36-bc03-a9115709b531",
                        "HardCondition": false,
                        "ObjectiveId": "09ecc77d-20f7-47ff-9144-2b4f544a0621",
                        "KillMethod": "sniperrifle"
                    }
                ]
            },
            {
                "Type": "statemachine",
                "Id": "d4e04980-d5ae-4d73-9823-cd278034640d",
                "Category": "secondary",
                "Definition": {
                    "Scope": "Hit",
                    "Context": {
                        "Targets": [
                            "9a179346-f61f-4239-b46e-0e540ee34082"
                        ]
                    },
                    "States": {
                        "Start": {
                            "Kill": [
                                {
                                    "Condition": {
                                        "$and": [
                                            {
                                                "$eq": [
                                                    "$Value.RepositoryId",
                                                    "9a179346-f61f-4239-b46e-0e540ee34082"
                                                ]
                                            },
                                            {
                                                "$eq": [
                                                    "$Value.OutfitIsHitmanSuit",
                                                    true
                                                ]
                                            }
                                        ]
                                    },
                                    "Transition": "Success"
                                },
                                {
                                    "Condition": {
                                        "$eq": [
                                            "$Value.RepositoryId",
                                            "9a179346-f61f-4239-b46e-0e540ee34082"
                                        ]
                                    },
                                    "Transition": "Failure"
                                }
                            ]
                        }
                    }
                }
            },
            {
                "Type": "statemachine",
                "Id": "09ecc77d-20f7-47ff-9144-2b4f544a0621",
                "Category": "secondary",
                "Definition": {
                    "Scope": "Hit",
                    "Context": {
                        "Targets": [
                            "9a179346-f61f-4239-b46e-0e540ee34082"
                        ]
                    },
                    "States": {
                        "Start": {
                            "Kill": [
                                {
                                    "Condition": {
                                        "$and": [
                                            {
                                                "$eq": [
                                                    "$Value.RepositoryId",
                                                    "9a179346-f61f-4239-b46e-0e540ee34082"
                                                ]
                                            },
                                            {
                                                "$any": {
                                                    "?": {
                                                        "$eq": [
                                                            "$.#",
                                                            "sniperrifle"
                                                        ]
                                                    },
                                                    "in": [
                                                        "$Value.KillMethodBroad",
                                                        "$Value.KillMethodStrict"
                                                    ]
                                                }
                                            }
                                        ]
                                    },
                                    "Transition": "Success"
                                },
                                {
                                    "Condition": {
                                        "$eq": [
                                            "$Value.RepositoryId",
                                            "9a179346-f61f-4239-b46e-0e540ee34082"
                                        ]
                                    },
                                    "Transition": "Failure"
                                }
                            ]
                        }
                    }
                }
            },
            {
                "Type": "statemachine",
                "Id": "c80f4e8e-14b3-44da-9ca7-52e69eaec732",
                "BriefingText": {
                    "$loc": {
                        "key": "UI_CONTRACT_GENERAL_OBJ_KILL",
                        "data": "$($repository ad583017-64e9-47e3-9734-0c4124d8e4c1).Name"
                    }
                },
                "HUDTemplate": {
                    "display": {
                        "$loc": {
                            "key": "UI_CONTRACT_GENERAL_OBJ_KILL",
                            "data": "$($repository ad583017-64e9-47e3-9734-0c4124d8e4c1).Name"
                        }
                    }
                },
                "Category": "primary",
                "Definition": {
                    "Scope": "Hit",
                    "Context": {
                        "Targets": [
                            "ad583017-64e9-47e3-9734-0c4124d8e4c1"
                        ]
                    },
                    "States": {
                        "Start": {
                            "Kill": [
                                {
                                    "Condition": {
                                        "$eq": [
                                            "$Value.RepositoryId",
                                            "ad583017-64e9-47e3-9734-0c4124d8e4c1"
                                        ]
                                    },
                                    "Transition": "Success"
                                }
                            ]
                        }
                    }
                },
                "TargetConditions": [
                    {
                        "Type": "hitmansuit",
                        "RepositoryId": "75759271-e236-4b33-8dd5-7e502c958d05",
                        "HardCondition": false,
                        "ObjectiveId": "6ae0977a-cc39-4097-b545-6c86aa720959",
                        "KillMethod": ""
                    },
                    {
                        "Type": "killmethod",
                        "RepositoryId": "1264f20b-b901-4d36-bc03-a9115709b531",
                        "HardCondition": false,
                        "ObjectiveId": "7b5c5cee-4f46-41db-b5ac-348c2db679dd",
                        "KillMethod": "sniperrifle"
                    }
                ]
            },
            {
                "Type": "statemachine",
                "Id": "6ae0977a-cc39-4097-b545-6c86aa720959",
                "Category": "secondary",
                "Definition": {
                    "Scope": "Hit",
                    "Context": {
                        "Targets": [
                            "ad583017-64e9-47e3-9734-0c4124d8e4c1"
                        ]
                    },
                    "States": {
                        "Start": {
                            "Kill": [
                                {
                                    "Condition": {
                                        "$and": [
                                            {
                                                "$eq": [
                                                    "$Value.RepositoryId",
                                                    "ad583017-64e9-47e3-9734-0c4124d8e4c1"
                                                ]
                                            },
                                            {
                                                "$eq": [
                                                    "$Value.OutfitIsHitmanSuit",
                                                    true
                                                ]
                                            }
                                        ]
                                    },
                                    "Transition": "Success"
                                },
                                {
                                    "Condition": {
                                        "$eq": [
                                            "$Value.RepositoryId",
                                            "ad583017-64e9-47e3-9734-0c4124d8e4c1"
                                        ]
                                    },
                                    "Transition": "Failure"
                                }
                            ]
                        }
                    }
                }
            },
            {
                "Type": "statemachine",
                "Id": "7b5c5cee-4f46-41db-b5ac-348c2db679dd",
                "Category": "secondary",
                "Definition": {
                    "Scope": "Hit",
                    "Context": {
                        "Targets": [
                            "ad583017-64e9-47e3-9734-0c4124d8e4c1"
                        ]
                    },
                    "States": {
                        "Start": {
                            "Kill": [
                                {
                                    "Condition": {
                                        "$and": [
                                            {
                                                "$eq": [
                                                    "$Value.RepositoryId",
                                                    "ad583017-64e9-47e3-9734-0c4124d8e4c1"
                                                ]
                                            },
                                            {
                                                "$any": {
                                                    "?": {
                                                        "$eq": [
                                                            "$.#",
                                                            "sniperrifle"
                                                        ]
                                                    },
                                                    "in": [
                                                        "$Value.KillMethodBroad",
                                                        "$Value.KillMethodStrict"
                                                    ]
                                                }
                                            }
                                        ]
                                    },
                                    "Transition": "Success"
                                },
                                {
                                    "Condition": {
                                        "$eq": [
                                            "$Value.RepositoryId",
                                            "ad583017-64e9-47e3-9734-0c4124d8e4c1"
                                        ]
                                    },
                                    "Transition": "Failure"
                                }
                            ]
                        }
                    }
                }
            }
        ],
        "GameChangers": [],
        "Bricks": []
    },
    "Metadata": {
        "Title": "Ordre d'assassinat : 1-03-5834041-10",
        "Description": "Un contrat a été placé, et vous avez été autorisé à engager le combat. Éliminez toutes les cibles le plus proprement possible, et faites en sorte d'éviter les dommages collatéraux.",
        "ScenePath": "assembly:/_PRO/Scenes/Missions/CoastalTown/_scene_octopus.entity",
        "Location": "LOCATION_COASTALTOWN",
        "IsPublished": true,
        "CreatorUserId": "8ca85fc9-1e68-46e0-a5b8-e1b42fd16e6b",
        "GameVersion": "7.17.0.0",
        "ServerVersion": "7.17.6.0",
        "Type": "usercreated",
        "Id": "345497ab-832d-4b6a-80aa-fd04bb85c1e9",
        "PublicId": "103583404110",
        "TileImage": "$($repository df5c1078-aa9e-4649-b5a4-e49ec984cc89).Image",
        "GroupObjectiveDisplayOrder": [
            {
                "Id": "2519ab48-537c-41ab-adab-98332315a2e5"
            },
            {
                "Id": "6a05b0f9-c79a-4d5b-9e69-2b52595b61ea"
            },
            {
                "Id": "acaf277c-c58b-4b7b-919e-448d12332d97"
            },
            {
                "Id": "690825bf-499d-4ad7-9b50-297e1b2763f4"
            },
            {
                "Id": "c80f4e8e-14b3-44da-9ca7-52e69eaec732"
            },
            {
                "Id": "00000000-0000-0000-0000-000000000000"
            },
            {
                "Id": "00000000-0000-0000-0000-000000000000"
            }
        ],
        "CreationTimestamp": "2019-12-21T14:08:57.62Z"
    },
    "UserData": {}
}