{
    "Data": {
        "Objectives": [
            {
                "Type": "statemachine",
                "Id": "f18967ef-7331-4097-a7b6-96ec028ce480",
                "BriefingText": {
                    "$loc": {
                        "key": "UI_CONTRACT_GENERAL_OBJ_KILL",
                        "data": "$($repository efb0894c-426e-4f66-9822-880d1e735047).Name"
                    }
                },
                "HUDTemplate": {
                    "display": {
                        "$loc": {
                            "key": "UI_CONTRACT_GENERAL_OBJ_KILL",
                            "data": "$($repository efb0894c-426e-4f66-9822-880d1e735047).Name"
                        }
                    }
                },
                "Category": "primary",
                "Definition": {
                    "Scope": "Hit",
                    "Context": {
                        "Targets": [
                            "efb0894c-426e-4f66-9822-880d1e735047"
                        ]
                    },
                    "States": {
                        "Start": {
                            "Kill": [
                                {
                                    "Condition": {
                                        "$eq": [
                                            "$Value.RepositoryId",
                                            "efb0894c-426e-4f66-9822-880d1e735047"
                                        ]
                                    },
                                    "Transition": "Success"
                                }
                            ]
                        }
                    }
                }
            },
            {
                "Type": "statemachine",
                "Id": "6355430b-563c-4c17-98aa-6a4d7b605328",
                "BriefingText": {
                    "$loc": {
                        "key": "UI_CONTRACT_GENERAL_OBJ_KILL",
                        "data": "$($repository 0b06a237-7e19-46ec-bfa8-2cb6826dface).Name"
                    }
                },
                "HUDTemplate": {
                    "display": {
                        "$loc": {
                            "key": "UI_CONTRACT_GENERAL_OBJ_KILL",
                            "data": "$($repository 0b06a237-7e19-46ec-bfa8-2cb6826dface).Name"
                        }
                    }
                },
                "Category": "primary",
                "Definition": {
                    "Scope": "Hit",
                    "Context": {
                        "Targets": [
                            "0b06a237-7e19-46ec-bfa8-2cb6826dface"
                        ]
                    },
                    "States": {
                        "Start": {
                            "Kill": [
                                {
                                    "Condition": {
                                        "$eq": [
                                            "$Value.RepositoryId",
                                            "0b06a237-7e19-46ec-bfa8-2cb6826dface"
                                        ]
                                    },
                                    "Transition": "Success"
                                }
                            ]
                        }
                    }
                }
            },
            {
                "Type": "statemachine",
                "Id": "5f99c2bc-3793-4d8e-809b-ba1b40337d38",
                "BriefingText": {
                    "$loc": {
                        "key": "UI_CONTRACT_GENERAL_OBJ_KILL",
                        "data": "$($repository ea65261d-d657-4e7f-8e3b-7027e637e673).Name"
                    }
                },
                "HUDTemplate": {
                    "display": {
                        "$loc": {
                            "key": "UI_CONTRACT_GENERAL_OBJ_KILL",
                            "data": "$($repository ea65261d-d657-4e7f-8e3b-7027e637e673).Name"
                        }
                    }
                },
                "Category": "primary",
                "Definition": {
                    "Scope": "Hit",
                    "Context": {
                        "Targets": [
                            "ea65261d-d657-4e7f-8e3b-7027e637e673"
                        ]
                    },
                    "States": {
                        "Start": {
                            "Kill": [
                                {
                                    "Condition": {
                                        "$eq": [
                                            "$Value.RepositoryId",
                                            "ea65261d-d657-4e7f-8e3b-7027e637e673"
                                        ]
                                    },
                                    "Transition": "Success"
                                }
                            ]
                        }
                    }
                }
            }
        ],
        "GameChangers": [],
        "Bricks": []
    },
    "Metadata": {
        "Title": "Kill Order: 1-08-1663960-07",
        "Description": "A contract has been issued, and you have been cleared to engage. Eliminate any targets as cleanly as possible, avoiding collateral damage as far as possible.",
        "ScenePath": "assembly:/_PRO/Scenes/Missions/Bangkok/_scene_tiger.entity",
        "Location": "LOCATION_BANGKOK",
        "IsPublished": true,
        "CreatorUserId": "b5554853-c809-416a-bafd-15cf1125d53f",
        "GameVersion": "7.17.0.0",
        "ServerVersion": "7.21.0.18",
        "Type": "usercreated",
        "Id": "3d1b75c1-69ed-4b19-82aa-039c9de9780c",
        "PublicId": "108166396007",
        "TileImage": "$($repository efb0894c-426e-4f66-9822-880d1e735047).Image",
        "GroupObjectiveDisplayOrder": [
            {
                "Id": "f18967ef-7331-4097-a7b6-96ec028ce480"
            },
            {
                "Id": "6355430b-563c-4c17-98aa-6a4d7b605328"
            },
            {
                "Id": "5f99c2bc-3793-4d8e-809b-ba1b40337d38"
            },
            {
                "Id": "00000000-0000-0000-0000-000000000000"
            },
            {
                "Id": "00000000-0000-0000-0000-000000000000"
            }
        ],
        "CreationTimestamp": "2022-06-23T21:06:18.4117387Z"
    },
    "UserData": {}
}